{
    "inspection_id": "INS_1780137668_84b364",
    "timestamp": "2026-05-30T10:41:08Z",
    "image_path": "data/images/empty_shelf_train_4583_jpg.rf.4e9013fc24e98d9abeb96e86aa711fe8.jpg",
    "zone_id": "Z_EMP",
    "overall_status": "warning",
    "issues": [
        {
            "issue_id": "ISS_001",
            "type": "empty_shelf",
            "location": "prateleira",
            "severity": "medium",
            "description": "Prateleira parcialmente vazia (229 produtos, ocupação de 13.9%).",
            "confidence": 0.9,
            "affected_area_pct": 86.1
        }
    ],
    "shelf_fill_rate": 13.9,
    "products_detected": [
        "retalho"
    ],
    "model_reasoning": "CoT Visual: 1. Descrição: Prateleira de empty. 2. Identificação: Prateleira parcialmente vazia (229 produtos, ocupação de 13.9%).. 3. Classificação: empty_shelf. 4. Conclusão: Status warning."
}