{
    "inspection_id": "INS_1780479114_f25594",
    "timestamp": "2026-06-03T09:31:54Z",
    "image_path": "data/images/planogram_violation_test_869_jpg.rf.40c3053db1e681e0048e46325a3ac052.jpg",
    "zone_id": "Z_PLA",
    "overall_status": "warning",
    "issues": [
        {
            "issue_id": "ISS_001",
            "type": "wrong_product",
            "location": "prateleira",
            "severity": "medium",
            "description": "Violação de planograma detetada: 8 produtos tombados de lado.",
            "confidence": 0.85,
            "affected_area_pct": 15.0
        }
    ],
    "shelf_fill_rate": 85.0,
    "products_detected": [
        "retalho"
    ],
    "model_reasoning": "Zero-shot: Observado estado warning com fill rate 85.0%."
}